azureml/__init__.py
azureml/pipeline/__init__.py
azureml/pipeline/_cli_wrapper/__init__.py
azureml/pipeline/_cli_wrapper/cmd_pipeline.py
azureml/pipeline/core/__init__.py
azureml/pipeline/core/_adla_step_base.py
azureml/pipeline/core/_aeva_provider.py
azureml/pipeline/core/_annotated_arguments.py
azureml/pipeline/core/_azurebatch_step_base.py
azureml/pipeline/core/_data_transfer_step_base.py
azureml/pipeline/core/_databricks_step_base.py
azureml/pipeline/core/_datasource_builder.py
azureml/pipeline/core/_graph_context.py
azureml/pipeline/core/_hdinsight_step_base.py
azureml/pipeline/core/_kusto_step_base.py
azureml/pipeline/core/_module_builder.py
azureml/pipeline/core/_module_parameter_provider.py
azureml/pipeline/core/_parallel_run_config_base.py
azureml/pipeline/core/_parallel_run_step_base.py
azureml/pipeline/core/_pipeline_yaml_parser.py
azureml/pipeline/core/_python_script_step_base.py
azureml/pipeline/core/_synapse_spark_step_base.py
azureml/pipeline/core/_workflow_provider.py
azureml/pipeline/core/_yaml_keys.py
azureml/pipeline/core/builder.py
azureml/pipeline/core/graph.py
azureml/pipeline/core/module.py
azureml/pipeline/core/module_step_base.py
azureml/pipeline/core/pipeline.py
azureml/pipeline/core/pipeline_draft.py
azureml/pipeline/core/pipeline_endpoint.py
azureml/pipeline/core/pipeline_output_dataset.py
azureml/pipeline/core/run.py
azureml/pipeline/core/schedule.py
azureml/pipeline/core/_restclients/__init__.py
azureml/pipeline/core/_restclients/aeva/__init__.py
azureml/pipeline/core/_restclients/aeva/aml_pipelines_api10.py
azureml/pipeline/core/_restclients/aeva/azure_storage.py
azureml/pipeline/core/_restclients/aeva/dryrun_service_caller.py
azureml/pipeline/core/_restclients/aeva/service_caller.py
azureml/pipeline/core/_restclients/aeva/service_caller_base.py
azureml/pipeline/core/_restclients/aeva/version.py
azureml/pipeline/core/_restclients/aeva/models/__init__.py
azureml/pipeline/core/_restclients/aeva/models/argument_assignment.py
azureml_pipeline_core-1.60.0.dist-info/licenses/LICENSE.txt
azureml_pipeline_core-1.60.0.dist-info/METADATA
azureml_pipeline_core-1.60.0.dist-info/WHEEL
azureml_pipeline_core-1.60.0.dist-info/entry_points.txt
azureml_pipeline_core-1.60.0.dist-info/top_level.txt
azureml_pipeline_core-1.60.0.dist-info/RECORD
