Metadata-Version: 2.4
Name: azureml-pipeline-core
Version: 1.60.0
Summary: Contains core functionality for Azure Machine Learning pipelines, which are configurable machine learning workflows.
Author: Microsoft Corp
License: https://aka.ms/azureml-sdk-license
Keywords: ipython,jupyter,widgets
Classifier: Development Status :: 4 - Beta
Classifier: Framework :: IPython
Classifier: Intended Audience :: Developers
Classifier: Intended Audience :: Science/Research
Classifier: Topic :: Multimedia :: Graphics
Classifier: Programming Language :: Python :: 3
Classifier: Programming Language :: Python :: 3.8
Classifier: Programming Language :: Python :: 3.9
Classifier: Programming Language :: Python :: 3.10
Classifier: Programming Language :: Python :: 3.11
Requires-Python: >=3.8,<4.0
License-File: LICENSE.txt
Requires-Dist: azureml-core~=1.60.0
Dynamic: author
Dynamic: classifier
Dynamic: description
Dynamic: description-content-type
Dynamic: keywords
Dynamic: license
Dynamic: license-file
Dynamic: requires-dist
Dynamic: requires-python
Dynamic: summary
